nyaascrape/__init__.py
nyaascrape/nyaascrape.py
nyaascrape-1.0.0.dist-info/LICENSE.txt
nyaascrape-1.0.0.dist-info/METADATA
nyaascrape-1.0.0.dist-info/WHEEL
nyaascrape-1.0.0.dist-info/top_level.txt
nyaascrape-1.0.0.dist-info/RECORD
